{
    "descr": "sample6",

    "nodes": [
        { "name": "A", "r": "6", "color": "#CD5C5C", "link": "" },
        { "name": "B", "r": "6", "color": "#CD5C5C", "link": "" },
        { "name": "C", "r": "6", "color": "#CD5C5C", "link": "" },
        { "name": "D", "r": "6", "color": "#CD5C5C", "link": "" }
    ],

    "lines": [
        { "source": "A", "target": "B","color": "#6495ED", "width": "1", "descr": "1", "link": "" },
        { "source": "B", "target": "C","color": "#B22222", "width": "1", "descr": "2", "link": "" },
        { "source": "C", "target": "D","color": "#2E8B57", "width": "1", "descr": "3", "link": "" },
        { "source": "A", "target": "D","color": "#FF8C00", "width": "1", "descr": "4", "link": "" },
        { "source": "A", "target": "D","color": "#DB7093", "width": "1", "descr": "5", "link": "" }
    ]
}
	
